.coveragerc
.gitignore
.travis.yml
CONTRIBUTING.rst
DESCRIPTION
README.md
manage.py
requirements_test.txt
runtests.py
setup.py
table_select_widget.png
tox.ini
django_table_select_widget.egg-info/PKG-INFO
django_table_select_widget.egg-info/SOURCES.txt
django_table_select_widget.egg-info/dependency_links.txt
django_table_select_widget.egg-info/requires.txt
django_table_select_widget.egg-info/top_level.txt
table_select_widget/__init__.py
tests/__init__.py
tests/models.py
tests/settings.py
tests/test_widget.py
tests/migrations/0001_initial.py
tests/migrations/__init__.py