Metadata-Version: 1.1
Name: django-table-select-widget
Version: 1.0.0
Summary: A Django widget for use with a ModelMultipleChoiceField to allow easy jQuery DataTables sorting and pagination by rendering the selector as a table.
